jackdyeruktaxcalculator/__init__.py
jackdyeruktaxcalculator/uk_tax_calculator.py
test/__init__.py
test/test_income_calculator.py
jackdyeruktaxcalculator-0.0.7.dist-info/LICENSE
jackdyeruktaxcalculator-0.0.7.dist-info/METADATA
jackdyeruktaxcalculator-0.0.7.dist-info/WHEEL
jackdyeruktaxcalculator-0.0.7.dist-info/top_level.txt
jackdyeruktaxcalculator-0.0.7.dist-info/RECORD
